{
	"animations": [
		{
			"loop": false,
			"offsets": [
				147,
				-12
			],
			"anim": "singLEFT",
			"fps": 24,
			"name": "CleveLand left",
			"indices": []
		},
		{
			"loop": false,
			"offsets": [
				27,
				-7
			],
			"anim": "singDOWN",
			"fps": 24,
			"name": "CleveLand down",
			"indices": []
		},
		{
			"loop": false,
			"offsets": [
				10,
				24
			],
			"anim": "singUP",
			"fps": 24,
			"name": "CleveLand up",
			"indices": []
		},
		{
			"loop": false,
			"offsets": [
				19,
				0
			],
			"anim": "idle",
			"fps": 24,
			"name": "CleveLand idle",
			"indices": []
		},
		{
			"loop": false,
			"offsets": [
				-35,
				0
			],
			"anim": "singRIGHT",
			"fps": 24,
			"name": "CleveLand right",
			"indices": []
		}
	],
	"no_antialiasing": true,
	"image": "characters/CleveLand2",
	"position": [
		-70,
		0
	],
	"healthicon": "squad2",
	"flip_x": true,
	"healthbar_colors": [
		100,
		120,
		175
	],
	"camera_position": [
		0,
		0
	],
	"sing_duration": 6.1,
	"scale": 0.9
}